product_id_extractor/__init__.py
product_id_extractor/config.py
product_id_extractor_yimian-0.0.4.dist-info/METADATA
product_id_extractor_yimian-0.0.4.dist-info/WHEEL
product_id_extractor_yimian-0.0.4.dist-info/top_level.txt
product_id_extractor_yimian-0.0.4.dist-info/RECORD
